pylexitext/__init__.py
pylexitext/downloader.py
pylexitext/plots.py
pylexitext/text.py
pylexitext/text_bean.py
pylexitext/text_converter.py
pylexitext-0.3.1.dist-info/LICENSE
pylexitext-0.3.1.dist-info/METADATA
pylexitext-0.3.1.dist-info/WHEEL
pylexitext-0.3.1.dist-info/top_level.txt
pylexitext-0.3.1.dist-info/RECORD
