Metadata-Version: 2.1
Name: pylexitext
Version: 0.3.1
Summary: Pylexitext is a python library that aggregates a series of NLP methods, text analysis, content converters and other usefull stuff.
Home-page: https://github.com/vicotrbb/Pylexitext
Author: Victor Bona
Author-email: victor.bona@hotmail.com
License: MIT
Download-URL: https://pypi.org/project/pylexitext/
Project-URL: Bug Tracker, https://github.com/vicotrbb/Pylexitext/issues
Project-URL: Source Code, https://github.com/vicotrbb/Pylexitext
Keywords: NLP,readability,nltk,text,Python3,data-science
Platform: UNKNOWN
Classifier: Programming Language :: Python
Classifier: Programming Language :: Python :: 3
Classifier: Programming Language :: Python :: 3.5
Classifier: Programming Language :: Python :: 3.6
Classifier: Programming Language :: Python :: 3.7
Classifier: Programming Language :: Python :: 3.8
Classifier: Programming Language :: Python :: 3 :: Only
Classifier: Intended Audience :: Developers
Classifier: Intended Audience :: Education
Classifier: Intended Audience :: Science/Research
Classifier: Topic :: Text Processing
Classifier: Operating System :: OS Independent
Requires-Python: >=3.5
Requires-Dist: numpy
Requires-Dist: nltk
Requires-Dist: networkx
Requires-Dist: matplotlib
